{
  "name" : "num",
  "states":
  {
    "q0":
    {
      "initial" : true,
      "final"   : false,
      "productions" :
      {
        "0" : "q1",
        "1" : "q1",
        "2" : "q1",
        "3" : "q1",
        "4" : "q1",
        "5" : "q1",
        "6" : "q1",
        "7" : "q1",
        "8" : "q1",
        "9" : "q1"
      }
    },
    "q1":
    {
      "initial" : false,
      "final"   : true,
      "productions" :
      {
        "0" : "q1",
        "1" : "q1",
        "2" : "q1",
        "3" : "q1",
        "4" : "q1",
        "5" : "q1",
        "6" : "q1",
        "7" : "q1",
        "8" : "q1",
        "9" : "q1"
      }
    }
  }
}